Workbook

Sheet Commercial (Met meerwerk)
B2: COMMERCIAL PRESENTATION
B4: Description | C4: Hrs | D4: Split | E4: Rate | F4: Amount
B5: Design & Development
B6: Requirements analysis | C6: =0.15*'Commercial (Met meerwerk)'!C9 -> 24.3 | D6: =Estimate!B13 -> 0.1 | E6: 27.5 | F6: =C6*E6 -> 668.25
B7: UI/UX design | C7: =C9*0.05 -> 8.1 | D7: =Estimate!B14 -> 0.05 | E7: 27.5 | F7: =C7*E7 -> 222.75
B8: Architecture & detailed design | C8: =0.1*C9 -> 16.2 | D8: =Estimate!B13 -> 0.1 | E8: 27.5 | F8: =C8*E8 -> 445.5
B9: Frontend & Backend | C9: =FunctionalitiesBreakdown!E27 -> 162 | D9: 1 | E9: 27.5 | F9: =C9*E9 -> 4455
B11: Total development | C11: =SUBTOTAL(109,C5:C10) -> 210.6 | D11: =D6+D9+D7 -> 1.15 | E11: =F11/C11 -> 27.5 | F11: =SUBTOTAL(109,F5:F10) -> 5791.5
B13: Quality Control & Deployment
B14: Development Testing | C14: =0.15*C9 -> 24.3 | D14: 0.15 | E14: 24 | F14: =C14*E14 -> 583.2
B15: Unit test & quality improvement | C15: =0*C9 -> 0 | D15: =C15/$C$20 -> 0 | E15: 25.75 | F15: =C15*E15 -> 0
B16: Deployment Stage & Production | C16: =0.05*C9 -> 8.1 | D16: =Estimate!B16 -> 0.1 | E16: 38.5 | F16: =C16*E16 -> 311.85
B17: Transition & acceptance | C17: =0.05*C9 -> 8.1 | D17: =Estimate!B19 -> 0.1 | E17: 38.5 | F17: =C17*E17 -> 311.85
B18: Regression Testing | D18: =C18/$C$20 -> 0 | E18: 24 | F18: =C18*E18 -> 0
B19: Dev server | F19: 93
B20: Total QC & Deployment | C20: =SUM(C14:C18) -> 40.5 | D20: =SUBTOTAL(109,D14:D18) -> 0.35 | E20: =F20/C20 -> 32.096296 | F20: =SUBTOTAL(109,F14:F19) -> 1299.9
B22: Total direct production | C22: =C11+C20 -> 251.1 | F22: =F11+F20 -> 7091.4
B24: Project management | C24: =C9*Table3333[[#This Row],[Split]] -> 16.2 | D24: =Estimate!B20 -> 0.1 | E24: 38.5 | F24: =C24*E24 -> 623.7
B25: Project Time Material Budget | C25: =C22+C24 -> 267.3 | F25: =F22+F24 -> 7715.1
B26: Fixed Pricing Risk | C26: =D26*C25 -> 0 | D26: 0 | F26: =D26*F25 -> 0 | H26: Cost of work | I26: Margin | J26: Margin AF/BA (50%) | K26: Invoice AF to BA | L26: Invoice | M26: Status
B27: Project Fixed Price Budget | C27: =C25+C26 -> 267.3 | E27: =F27/C27 -> 28.863075 | F27: =F25+F26 -> 7715.1 | H27: ='CostOf Wok'!E12 -> 6370.2 | I27: =Table3333[[#This Row],[Amount]]-H27 -> 1344.9
G29: Deposit (50%) | H29: =H27/2 -> 3185.1 | K29: =H29 -> 3185.1
F30: =F27-F29 -> 7715.1 | G30: Betaling bij oplevering | H30: =H27-H29 -> 3185.1 | I30: =I27-I29 -> 1344.9 | J30: =I30/2 -> 672.45 | K30: =H30+J30 -> 3857.55
J31: Total for AIMFIRST VN | K31: =SUM(K29:K30) -> 7042.65

Sheet Estimate
A1: ESTIMATION SHEET
A2: Project: | B2: TT-AIM-SPRINT 8B
A3: Updated date: | B3: 15/1/2026
A4: Updated by: | B4: Phuc Le
A6: SUMMARY
A8: Implementation effort | B8: =FunctionalitiesBreakdown!E27 -> 162
A9: Duration | B9: 5 weeks | C9: (Tentative schedule)
A11: PROJECT ACTIVITIES | C11: GANTT CHART (WEEK)
A12: Activity | B12: Ratio | C12: W1 | D12: W2 | E12: W3 | F12: W4 | G12: W5
A13: Requirements analysis | B13: 0.1 | C13: x | D13: x | E13: x | F13: x | G13: x
A14: UI/UX design | B14: 0.05 | C14: x | D14: x | E14: x | F14: x | G14: x
A15: Architecture & detailed design | B15: 0.1 | C15: x | D15: x | E15: x | F15: x | G15: x
A16: Deployment environment Stage / Production | B16: 0.1 | F16: x | G16: x
A17: Implementation | B17: 1 | C17: x | D17: x | E17: x | F17: x | G17: x
A18: Quality control | B18: 0.15 | E18: x | F18: x | G18: x
A19: Transition & acceptance | B19: 0.1 | F19: x | G19: x
A20: Project management | B20: 0.1 | C20: x | D20: x | E20: x | F20: x | G20: x
A22: TEAM STRUCTURE
A23: Role | B23: Count
A24: DEV React JS | B24: 1 | C24: 1 | D24: 1 | E24: 1 | F24: 1 | G24: 1
A25: Backend dev (PHP) | B25: 2 | C25: 1 | D25: 1 | E25: 1 | F25: 1 | G25: 1
A26: Python dev | B26: 1
A27: QA | B27: 1 | D27: 1 | E27: 1 | F27: 1 | G27: 1
A28: Devops | B28: 1 | D28: 0.05 | E28: 0.05 | F28: 0.05 | G28: 0.05
A29: PM | B29: 1 | C29: 0.1 | D29: 0.1 | E29: 0.1 | F29: 0.1 | G29: 0.1
B30: =SUM(B24:B29) -> 7
A33: ASSUMPTIONS

Sheet CostOf Wok
A1: No | B1: Title | C1: Total hours | D1: Rate | E1: Total
A2: 1 | B2: Development (Implementation) PHP | C2: =FunctionalitiesBreakdown!E27 -> 162 | D2: 22 | E2: =C2*D2 -> 3564
A3: 3 | B3: =Estimate!A14 -> UI/UX design | C3: =Estimate!B14*'CostOf Wok'!C2 -> 8.1 | D3: 22 | E3: =C3*D3 -> 178.2
A4: 4 | B4: =Estimate!A15 -> Architecture & detailed design | C4: =Estimate!B15*'CostOf Wok'!C2 -> 16.2 | D4: 22 | E4: =C4*D4 -> 356.4
A5: 5 | B5: =Estimate!A13 -> Requirements analysis | C5: =C2*Estimate!B13 -> 16.2 | D5: 22 | E5: =C5*D5 -> 356.4
A6: 6 | B6: Quality control | C6: =C2*Estimate!B18 -> 24.3 | D6: 20 | E6: =C6*D6 -> 486
A7: 7 | B7: Project Manager | C7: =C2*Estimate!B20 -> 16.2 | D7: 25 | E7: =C7*D7 -> 405
A8: 8 | B8: Deployment (Devops) | C8: =C2*Estimate!B16 -> 16.2 | D8: 24 | E8: =C8*D8 -> 388.8
A9: 9 | B9: =Estimate!A19 -> Transition & acceptance | C9: =C2*Estimate!B19 -> 16.2 | D9: 22 | E9: =C9*D9 -> 356.4
A10: Total | C10: =SUM(C2:C9) -> 275.4 | E10: =SUM(E2:E9) -> 6091.2
B11: Dev Server fee | C11: 3 | D11: 93 | E11: =C11*D11 -> 279
A12: Total billing | E12: =E10+E11 -> 6370.2

Sheet FunctionalitiesBreakdown
A1: FUNCTIONALITIES BREAKDOWN TT-AIM-SPRINT-8C (8 tickets)
A2: No. | B2: Ticket number | C2: Title | D2: Breadown task | E2: Estimate (hours) | F2: Note
A3: 1 | B3: TT-2436 | C3: Implement measures AI misuse | D3: Deactivate subscription when abnormal usage is registered: - Tracked user login : 1hr - Count the number of times the user logs in and the factsheet visited to deactivate : 1hr - Display message: account deactivated: 1h - Define the deactivate option for each user and check it when the user logs in: 1hr | E3: 4
D4: Provide a warning signal in case of high usage: - send notify email : 1hr - Create notification: 1hr | E4: 2
D5: Implement ReCaptcha for page | E5: 4
D6: Add CSRF token for form | E6: 2
A7: 2 | B7: TT-2439 | C7: Improvement LPB for BargeInsights: Tanker Type specific LPB stats | D7: Change 1: instead of update the Python LPB app, we can update berth historical data function (Slim API) for ‘visits’, ‘visit duration’, and ‘waiting time’ : 4hrs | E7: 4
D8: Change 2 : update Python LPB app can run with all aset classes | E8: 8
D9: Change 3 & change 4 | E9: 8
A10: 3 | B10: TT-2434 | C10: Split Logistical Benchmarking in Logistical Performance and Product Flows as Non Stripe subscriptions | D10: Implement User story 1: 1. Non-Stripe Changes : 0.5hrs 2. Stripe Subscriptions: 0.5hrs 3. Subscription Inclusion Rules: 0.5hrs 4. Update old data (All existing non-Stripe users who currently have Logistical Benchmarking and therefore access to Product Flows): 1hr 5, Improvement on BI Package: 1hr | E10: 3.5
A11: 4 | B11: TT-2423 | C11: Logical Checks Dashboard | D11: User story 1: Logical Checks dashboard | E11: 0.5
D12: User story 2: Label classifications | E12: 2
D13: User story 3: Logical Check Rules | E13: 2
D14: User story 4: Logical check dashboard: - Render layout : -- Tab 1: 2hrs -- Tab 2: 4hrs -- Edit terminal : 6hrs - Execute Rules (has 30 rules) --> 32 hours - Approving and Revoking approved a Warning --> 1 hour - Check the approved warning in the Rule --> 1 hour | E14: 46
D15: User story 5 | E15: 8
A16: 5 | B16: TT-2444 | C16: Rhine CPP: Low and High and make available in API | D16: - Back Office – Gasoil - Back Office – Gasoiline - API requirements | E16: 4
A17: 6 | B17: TT-2435 | C17: Improvement on Ship and Terminal Modal | D17: User story 0 : Improvement of Terminal factsheet information | E17: 16 | F17: The current platform UI is desktop-optimized and not designed for mobile responsive layouts. For TT-2435 we propose implementing adaptive panel behavior for smaller laptop screens only. Full mobile responsiveness would require a larger UI refactor outside the scope of this ticket.
D18: User story 1: Access detailed terminal information from the map | E18: 24
D19: User story 2: Access Logistical Performance with berth overview widget | E19: 12
D20: User story 3: Access detailed ship information from the map and Past route | E20: 12
A21: 7 | B21: TT-2443 | C21: Process Historical Waiting Times Data
A27: Development hours | E27: =SUM(E3:E26) -> 162
F34: =20*15% -> 3
